{
  "repo": "openclaw/openclaw",
  "cluster_id": "gitcrawl-788-plan-wave-20260615-b",
  "mode": "plan",
  "run_id": "27519056052",
  "run_url": "https://github.com/openclaw/clownfish/actions/runs/27519056052",
  "head_sha": "30afd4b1d5fd5919294bee21d7dd4b30ef87b468",
  "workflow_conclusion": "success",
  "workflow_status": "completed",
  "workflow_created_at": "2026-06-15T01:40:26Z",
  "workflow_updated_at": "2026-06-15T01:41:11Z",
  "result_status": "planned",
  "source_job": "jobs/openclaw/inbox/gitcrawl-788-plan-wave-20260615-b.md",
  "published_at": "2026-06-15T02:20:44.663Z",
  "canonical": "#78091",
  "canonical_issue": "#78091",
  "canonical_pr": null,
  "summary": "Plan-only classification: #78091 remains the open canonical issue for the Open-WebUI session reuse bug. #78124 is an open related contributor PR that directly targets #78091, but it is not merge-ready or suitable for fixed-by closeout because the Real behavior proof check is failing and a maintainer comment says the branch needs updating against current main. No security-sensitive signal was detected and no closure, merge, or fix PR action is planned.",
  "actions": [
    {
      "target": "#78091",
      "action": "keep_canonical",
      "status": "planned",
      "classification": "canonical",
      "canonical": "#78091",
      "candidate_fix": "#78124",
      "reason": "#78091 is the best live canonical because it is the open source bug report with the full reproduction and the linked PR has unresolved proof/update blockers."
    },
    {
      "target": "#78124",
      "action": "keep_related",
      "status": "planned",
      "classification": "related",
      "canonical": "#78091",
      "candidate_fix": "#78124",
      "reason": "#78124 is a plausible related fix path for the canonical issue, but failing proof and branch update requirements block merge or fixed-by-candidate closeout in this cluster plan."
    }
  ],
  "action_counts": {
    "keep_canonical": 1,
    "keep_related": 1
  },
  "action_status_counts": {
    "planned": 2
  },
  "fix_counts": {},
  "apply_counts": {},
  "needs_human": [],
  "fix_actions": [],
  "apply_actions": []
}
