{
  "repo": "openclaw/openclaw",
  "cluster_id": "pr-inventory-mixed-20260615T110614-016",
  "mode": "plan",
  "run_id": "27542133436",
  "run_url": "https://github.com/openclaw/clownfish/actions/runs/27542133436",
  "head_sha": "025b85cf99216592f20139b88da91d38f50b7cb8",
  "workflow_conclusion": "success",
  "workflow_status": "completed",
  "workflow_created_at": "2026-06-15T11:09:13Z",
  "workflow_updated_at": "2026-06-15T11:12:06Z",
  "result_status": "planned",
  "source_job": "jobs/openclaw/inbox/pr-inventory-mixed-20260615T110614-016.md",
  "published_at": "2026-06-15T11:13:53.055Z",
  "canonical": null,
  "canonical_issue": null,
  "canonical_pr": null,
  "summary": "Plan-mode PR inventory classification only. No GitHub mutations are recommended because this shard has no shared canonical, merge/fix actions are blocked by job frontmatter, and low-signal/instant close permissions are disabled.",
  "actions": [
    {
      "target": "#89826",
      "action": "keep_independent",
      "status": "planned",
      "classification": "independent",
      "canonical": null,
      "candidate_fix": null,
      "reason": "Independent maintainer-owned feature PR; keep open for normal maintainer/author flow."
    },
    {
      "target": "#47589",
      "action": "keep_independent",
      "status": "planned",
      "classification": "independent",
      "canonical": null,
      "candidate_fix": null,
      "reason": "Independent bug-fix PR with proof gap; no duplicate/superseded evidence."
    },
    {
      "target": "#51926",
      "action": "keep_independent",
      "status": "planned",
      "classification": "independent",
      "canonical": null,
      "candidate_fix": null,
      "reason": "Independent small agents PR awaiting proof; keep open."
    },
    {
      "target": "#92603",
      "action": "needs_human",
      "status": "planned",
      "classification": "needs_human",
      "canonical": null,
      "candidate_fix": null,
      "reason": "Cannot safely classify or plan any close-style action without hydrated live state."
    },
    {
      "target": "#92594",
      "action": "needs_human",
      "status": "planned",
      "classification": "needs_human",
      "canonical": null,
      "candidate_fix": null,
      "reason": "Cannot safely classify or plan any close-style action without hydrated live state."
    },
    {
      "target": "#88180",
      "action": "keep_independent",
      "status": "planned",
      "classification": "independent",
      "canonical": null,
      "candidate_fix": null,
      "reason": "Independent ready-for-maintainer PR; no duplicate or closure basis."
    },
    {
      "target": "#88633",
      "action": "keep_independent",
      "status": "planned",
      "classification": "independent",
      "canonical": null,
      "candidate_fix": null,
      "reason": "Maintainer-owned draft PR should stay in maintainer workflow."
    },
    {
      "target": "#88885",
      "action": "keep_independent",
      "status": "planned",
      "classification": "independent",
      "canonical": null,
      "candidate_fix": null,
      "reason": "Independent recovery fix awaiting normal maintainer review."
    },
    {
      "target": "#91399",
      "action": "keep_independent",
      "status": "planned",
      "classification": "independent",
      "canonical": null,
      "candidate_fix": null,
      "reason": "Independent PR with proof gap; keep open."
    },
    {
      "target": "#91473",
      "action": "keep_independent",
      "status": "planned",
      "classification": "independent",
      "canonical": null,
      "candidate_fix": null,
      "reason": "Independent provider feature/fix PR awaiting proof."
    },
    {
      "target": "#91481",
      "action": "keep_independent",
      "status": "planned",
      "classification": "independent",
      "canonical": null,
      "candidate_fix": null,
      "reason": "Independent ready-for-maintainer PR; no dedupe or closure action."
    },
    {
      "target": "#91553",
      "action": "keep_independent",
      "status": "planned",
      "classification": "independent",
      "canonical": null,
      "candidate_fix": null,
      "reason": "Independent scripts/runtime fix with proof gap; keep open."
    },
    {
      "target": "#91600",
      "action": "keep_independent",
      "status": "planned",
      "classification": "independent",
      "canonical": null,
      "candidate_fix": null,
      "reason": "Independent ready-for-maintainer PR; no closure basis."
    },
    {
      "target": "#91870",
      "action": "keep_independent",
      "status": "planned",
      "classification": "independent",
      "canonical": null,
      "candidate_fix": null,
      "reason": "Independent provider metadata PR awaiting author/proof follow-up."
    },
    {
      "target": "#92346",
      "action": "keep_independent",
      "status": "planned",
      "classification": "independent",
      "canonical": null,
      "candidate_fix": null,
      "reason": "Independent agents recovery PR; keep open for maintainer/proof process."
    },
    {
      "target": "#92454",
      "action": "keep_independent",
      "status": "planned",
      "classification": "independent",
      "canonical": null,
      "candidate_fix": null,
      "reason": "Independent task maintenance PR; keep open."
    },
    {
      "target": "#92491",
      "action": "keep_independent",
      "status": "planned",
      "classification": "independent",
      "canonical": null,
      "candidate_fix": null,
      "reason": "Independent MCP config PR awaiting author/maintainer flow."
    },
    {
      "target": "#92495",
      "action": "keep_independent",
      "status": "planned",
      "classification": "independent",
      "canonical": null,
      "candidate_fix": null,
      "reason": "Independent provider catalog PR; keep open for maintainer review."
    },
    {
      "target": "#92521",
      "action": "needs_human",
      "status": "planned",
      "classification": "needs_human",
      "canonical": null,
      "candidate_fix": null,
      "reason": "Needs refreshed hydration before classification, especially because the job body references a security-boundary risk label."
    },
    {
      "target": "#92574",
      "action": "needs_human",
      "status": "planned",
      "classification": "needs_human",
      "canonical": null,
      "candidate_fix": null,
      "reason": "Cannot safely classify without hydrated live state."
    },
    {
      "target": "#91408",
      "action": "keep_independent",
      "status": "planned",
      "classification": "independent",
      "canonical": null,
      "candidate_fix": null,
      "reason": "Independent broad feature PR with failing checks; keep open for maintainer review."
    },
    {
      "target": "#91721",
      "action": "keep_independent",
      "status": "planned",
      "classification": "independent",
      "canonical": null,
      "candidate_fix": null,
      "reason": "Independent PR in active/re-review flow; no closure action without hydrated discussion."
    },
    {
      "target": "#91955",
      "action": "keep_independent",
      "status": "planned",
      "classification": "independent",
      "canonical": null,
      "candidate_fix": null,
      "reason": "Independent agents workspace PR awaiting author/proof follow-up."
    },
    {
      "target": "#92610",
      "action": "needs_human",
      "status": "planned",
      "classification": "needs_human",
      "canonical": null,
      "candidate_fix": null,
      "reason": "Cannot safely classify without hydrated live state."
    },
    {
      "target": "#88743",
      "action": "keep_independent",
      "status": "planned",
      "classification": "independent",
      "canonical": null,
      "candidate_fix": null,
      "reason": "Independent docs PR; low-signal closeout is disabled by job permissions."
    }
  ],
  "action_counts": {
    "keep_independent": 20,
    "needs_human": 5
  },
  "action_status_counts": {
    "planned": 25
  },
  "fix_counts": {},
  "apply_counts": {},
  "needs_human": [
    "#92603 missing hydrated live state in compacted preflight artifact.",
    "#92594 missing hydrated live state in compacted preflight artifact.",
    "#92521 missing hydrated live state in compacted preflight artifact and has a security-boundary risk label in the job body.",
    "#92574 missing hydrated live state in compacted preflight artifact.",
    "#92610 missing hydrated live state in compacted preflight artifact."
  ],
  "fix_actions": [],
  "apply_actions": []
}
