{
  "repo": "openclaw/openclaw",
  "cluster_id": "pr-inventory-ready_for_maintainer-20260615T154534-113",
  "mode": "plan",
  "run_id": "27560323972-1-115",
  "workflow_run_id": "27560323972",
  "run_attempt": "1",
  "matrix_index": "115",
  "run_url": "https://github.com/openclaw/clownfish/actions/runs/27560323972",
  "head_sha": "61d2d7a61eeb9d8fe22ed20cc15f46b2ff4a4bb2",
  "workflow_conclusion": "success",
  "workflow_status": "completed",
  "workflow_created_at": "2026-06-15T16:20:33Z",
  "workflow_updated_at": "2026-06-15T16:27:26Z",
  "result_status": "planned",
  "source_job": "jobs/openclaw/inbox/pr-inventory-ready_for_maintainer-20260615T154534-113.md",
  "published_at": "2026-06-22T06:55:46.914Z",
  "canonical": null,
  "canonical_issue": null,
  "canonical_pr": null,
  "summary": "Plan-only PR inventory classification. No shared canonical was selected because the job explicitly identifies this as an inventory shard, not a dedupe cluster. No GitHub mutations, merges, fix PRs, or closeouts are planned.",
  "actions": [
    {
      "target": "#83612",
      "action": "keep_independent",
      "status": "planned",
      "classification": "independent",
      "canonical": null,
      "candidate_fix": null,
      "reason": "Standalone PR with unresolved merge-readiness risk; keep out of dedupe/closeout automation."
    },
    {
      "target": "#86710",
      "action": "keep_closed",
      "status": "skipped",
      "classification": "superseded",
      "canonical": null,
      "candidate_fix": null,
      "reason": "Already closed in live preflight state."
    },
    {
      "target": "#86719",
      "action": "keep_independent",
      "status": "planned",
      "classification": "independent",
      "canonical": null,
      "candidate_fix": null,
      "reason": "Standalone candidate that should remain available for normal maintainer review."
    },
    {
      "target": "#86730",
      "action": "keep_independent",
      "status": "planned",
      "classification": "independent",
      "canonical": null,
      "candidate_fix": null,
      "reason": "Standalone candidate that should remain available for normal maintainer review."
    },
    {
      "target": "#83612",
      "action": "keep_independent",
      "status": "planned",
      "classification": "independent",
      "canonical": null,
      "candidate_fix": null,
      "reason": "Same hydrated PR as the earlier #83612 matrix entry; classified independently without mutation."
    },
    {
      "target": "#86733",
      "action": "keep_closed",
      "status": "skipped",
      "classification": "superseded",
      "canonical": null,
      "candidate_fix": null,
      "reason": "Already closed in live preflight state."
    },
    {
      "target": "#86744",
      "action": "keep_independent",
      "status": "planned",
      "classification": "independent",
      "canonical": null,
      "candidate_fix": null,
      "reason": "Standalone candidate with unresolved validation visibility; keep for normal maintainer review."
    },
    {
      "target": "#86759",
      "action": "keep_independent",
      "status": "planned",
      "classification": "independent",
      "canonical": null,
      "candidate_fix": null,
      "reason": "Standalone candidate with unresolved validation visibility; keep for normal maintainer review."
    },
    {
      "target": "#86873",
      "action": "keep_independent",
      "status": "planned",
      "classification": "independent",
      "canonical": null,
      "candidate_fix": null,
      "reason": "Standalone candidate with unresolved validation visibility; keep for normal maintainer review."
    },
    {
      "target": "#86915",
      "action": "keep_independent",
      "status": "planned",
      "classification": "independent",
      "canonical": null,
      "candidate_fix": null,
      "reason": "Draft/low-signal-docs candidate is not eligible for automated low-signal closeout in this job."
    },
    {
      "target": "#86925",
      "action": "keep_independent",
      "status": "planned",
      "classification": "independent",
      "canonical": null,
      "candidate_fix": null,
      "reason": "Standalone candidate; translation correctness requires normal maintainer/localization review rather than cluster cleanup."
    },
    {
      "target": "#86971",
      "action": "keep_independent",
      "status": "planned",
      "classification": "independent",
      "canonical": null,
      "candidate_fix": null,
      "reason": "Standalone docs candidate with trust-boundary-sensitive content; keep for maintainer review."
    },
    {
      "target": "#87255",
      "action": "keep_independent",
      "status": "planned",
      "classification": "independent",
      "canonical": null,
      "candidate_fix": null,
      "reason": "Standalone candidate with unresolved review/validation visibility; keep for normal maintainer and author follow-up."
    },
    {
      "target": "#87273",
      "action": "keep_independent",
      "status": "planned",
      "classification": "independent",
      "canonical": null,
      "candidate_fix": null,
      "reason": "Standalone provider/auth diagnostic candidate; keep for normal maintainer and author follow-up."
    },
    {
      "target": "#84896",
      "action": "keep_independent",
      "status": "planned",
      "classification": "independent",
      "canonical": null,
      "candidate_fix": null,
      "reason": "Standalone broad contributor PR with author-follow-up and validation gaps; keep for normal maintainer review, not automated closeout."
    },
    {
      "target": "#87300",
      "action": "needs_human",
      "status": "planned",
      "classification": "needs_human",
      "canonical": null,
      "candidate_fix": null,
      "reason": "Maintainer judgment is needed on whether this develop-targeted, large UI PR belongs in this main-branch ready-for-maintainer inventory path."
    },
    {
      "target": "#87349",
      "action": "keep_independent",
      "status": "planned",
      "classification": "independent",
      "canonical": null,
      "candidate_fix": null,
      "reason": "Standalone trust-boundary-adjacent candidate; keep for normal maintainer and author follow-up without route_security because preflight marked it non-security-sensitive."
    },
    {
      "target": "#87373",
      "action": "keep_independent",
      "status": "planned",
      "classification": "independent",
      "canonical": null,
      "candidate_fix": null,
      "reason": "Standalone risky-infra script candidate; keep for normal maintainer and author follow-up."
    },
    {
      "target": "#87393",
      "action": "keep_independent",
      "status": "planned",
      "classification": "independent",
      "canonical": null,
      "candidate_fix": null,
      "reason": "Standalone candidate with validation visibility gaps; keep for normal maintainer review."
    },
    {
      "target": "#87478",
      "action": "keep_independent",
      "status": "planned",
      "classification": "independent",
      "canonical": null,
      "candidate_fix": null,
      "reason": "Standalone auth-provider config candidate; keep for normal maintainer and author follow-up."
    },
    {
      "target": "#87481",
      "action": "keep_independent",
      "status": "planned",
      "classification": "independent",
      "canonical": null,
      "candidate_fix": null,
      "reason": "Standalone candidate; no hydrated superseded target is available for closeout planning in this cluster."
    },
    {
      "target": "#87529",
      "action": "keep_independent",
      "status": "planned",
      "classification": "independent",
      "canonical": null,
      "candidate_fix": null,
      "reason": "Draft broad feature PR remains standalone and should not be closed or advanced by this inventory worker."
    },
    {
      "target": "#87530",
      "action": "keep_independent",
      "status": "planned",
      "classification": "independent",
      "canonical": null,
      "candidate_fix": null,
      "reason": "Standalone channel fix candidate; keep for normal maintainer and author follow-up."
    },
    {
      "target": "#87560",
      "action": "keep_independent",
      "status": "planned",
      "classification": "independent",
      "canonical": null,
      "candidate_fix": null,
      "reason": "Standalone candidate; keep for normal maintainer review."
    },
    {
      "target": "#87568",
      "action": "keep_independent",
      "status": "planned",
      "classification": "independent",
      "canonical": null,
      "candidate_fix": null,
      "reason": "Standalone broad UI/dependency feature PR; keep for normal maintainer and author follow-up."
    }
  ],
  "action_counts": {
    "keep_independent": 22,
    "keep_closed": 2,
    "needs_human": 1
  },
  "action_status_counts": {
    "planned": 23,
    "skipped": 2
  },
  "fix_counts": {},
  "apply_counts": {},
  "needs_human": [
    "#87300: maintainer judgment needed on develop-base PR routing versus the main-branch ready-for-maintainer inventory path."
  ],
  "repair_candidate": null,
  "fix_actions": [],
  "apply_actions": [],
  "apply_audit_actions": []
}
