{
  "repo": "openclaw/openclaw",
  "cluster_id": "live-pr-inventory-20260701T092542-001",
  "mode": "autonomous",
  "run_id": "28507541525",
  "workflow_run_id": "28507541525",
  "run_attempt": "1",
  "matrix_index": null,
  "run_url": "https://github.com/openclaw/clownfish/actions/runs/28507541525",
  "head_sha": "c96bc89600ddf477ca5b771d25bbb32dd484a96f",
  "workflow_conclusion": "success",
  "workflow_status": "completed",
  "workflow_created_at": "2026-07-01T09:26:43Z",
  "workflow_updated_at": "2026-07-01T09:35:05Z",
  "result_status": "planned",
  "source_job": "jobs/openclaw/inbox/live-pr-inventory-20260701T092542-001.md",
  "published_at": "2026-07-01T09:35:55.293Z",
  "canonical": null,
  "canonical_issue": null,
  "canonical_pr": null,
  "summary": "Four seed PRs are narrow docs candidates with passing hydrated checks and no security-sensitive signal. None should be merged by this worker because the deterministic exact-head validation and fresh Codex /review preflight are still missing; each seed PR is routed as a blocked merge_candidate for external merge preflight.",
  "actions": [
    {
      "target": "#96122",
      "action": "merge_candidate",
      "status": "blocked",
      "classification": "canonical",
      "canonical": "#55888",
      "candidate_fix": null,
      "reason": "external_merge_preflight_required"
    },
    {
      "target": "#96275",
      "action": "merge_candidate",
      "status": "blocked",
      "classification": "canonical",
      "canonical": "#78495",
      "candidate_fix": null,
      "reason": "external_merge_preflight_required"
    },
    {
      "target": "#96375",
      "action": "merge_candidate",
      "status": "blocked",
      "classification": "canonical",
      "canonical": null,
      "candidate_fix": null,
      "reason": "external_merge_preflight_required"
    },
    {
      "target": "#97753",
      "action": "merge_candidate",
      "status": "blocked",
      "classification": "canonical",
      "canonical": "#97752",
      "candidate_fix": null,
      "reason": "external_merge_preflight_required"
    },
    {
      "target": "#55888",
      "action": "keep_canonical",
      "status": "planned",
      "classification": "canonical",
      "canonical": null,
      "candidate_fix": "#96122",
      "reason": null
    },
    {
      "target": "#78495",
      "action": "keep_canonical",
      "status": "planned",
      "classification": "canonical",
      "canonical": null,
      "candidate_fix": "#96275",
      "reason": null
    },
    {
      "target": "#80396",
      "action": "keep_related",
      "status": "planned",
      "classification": "related",
      "canonical": "#78495",
      "candidate_fix": null,
      "reason": null
    },
    {
      "target": "#81176",
      "action": "keep_related",
      "status": "planned",
      "classification": "related",
      "canonical": "#55888",
      "candidate_fix": null,
      "reason": null
    },
    {
      "target": "#87932",
      "action": "keep_related",
      "status": "planned",
      "classification": "related",
      "canonical": "#55888",
      "candidate_fix": null,
      "reason": null
    },
    {
      "target": "#94389",
      "action": "keep_closed",
      "status": "skipped",
      "classification": "superseded",
      "canonical": "#78495",
      "candidate_fix": "#96275",
      "reason": null
    },
    {
      "target": "#94436",
      "action": "keep_closed",
      "status": "skipped",
      "classification": "superseded",
      "canonical": "#78495",
      "candidate_fix": "#96275",
      "reason": null
    },
    {
      "target": "#97752",
      "action": "keep_closed",
      "status": "skipped",
      "classification": "fixed_by_candidate",
      "canonical": null,
      "candidate_fix": "#97753",
      "reason": null
    }
  ],
  "action_counts": {
    "merge_candidate": 4,
    "keep_canonical": 2,
    "keep_related": 3,
    "keep_closed": 3
  },
  "action_status_counts": {
    "blocked": 4,
    "planned": 5,
    "skipped": 3
  },
  "fix_counts": {},
  "apply_counts": {
    "skipped": 4
  },
  "needs_human": [],
  "repair_candidate": null,
  "fix_actions": [],
  "apply_actions": [
    {
      "target": "#96122",
      "action": "merge_candidate",
      "status": "skipped",
      "classification": "canonical",
      "canonical": "#55888",
      "candidate_fix": null,
      "title": null,
      "idempotency_key": "clownfish:live-pr-inventory-20260701T092542-001:#96122:merge_candidate:external_preflight:a5b9f94eac35776b170a14daa7f0d4645698b8ac",
      "source_status": "blocked",
      "source_reason": "external_merge_preflight_required",
      "reason": "action status is blocked",
      "merged_at": null,
      "merge_commit_sha": null,
      "expected_head_sha": null,
      "live_state": null,
      "live_updated_at": null,
      "apply_attempt": 1,
      "applied_at": "2026-07-01T09:34:56.856Z",
      "report_source": "apply"
    },
    {
      "target": "#96275",
      "action": "merge_candidate",
      "status": "skipped",
      "classification": "canonical",
      "canonical": "#78495",
      "candidate_fix": null,
      "title": null,
      "idempotency_key": "clownfish:live-pr-inventory-20260701T092542-001:#96275:merge_candidate:external_preflight:720a6312fb0ece0da4418eb42b48d8e19c7b7d28",
      "source_status": "blocked",
      "source_reason": "external_merge_preflight_required",
      "reason": "action status is blocked",
      "merged_at": null,
      "merge_commit_sha": null,
      "expected_head_sha": null,
      "live_state": null,
      "live_updated_at": null,
      "apply_attempt": 1,
      "applied_at": "2026-07-01T09:34:56.856Z",
      "report_source": "apply"
    },
    {
      "target": "#96375",
      "action": "merge_candidate",
      "status": "skipped",
      "classification": "canonical",
      "canonical": null,
      "candidate_fix": null,
      "title": null,
      "idempotency_key": "clownfish:live-pr-inventory-20260701T092542-001:#96375:merge_candidate:external_preflight:d690d8967dc043b48a5359733ac1d1792110a42b",
      "source_status": "blocked",
      "source_reason": "external_merge_preflight_required",
      "reason": "action status is blocked",
      "merged_at": null,
      "merge_commit_sha": null,
      "expected_head_sha": null,
      "live_state": null,
      "live_updated_at": null,
      "apply_attempt": 1,
      "applied_at": "2026-07-01T09:34:56.856Z",
      "report_source": "apply"
    },
    {
      "target": "#97753",
      "action": "merge_candidate",
      "status": "skipped",
      "classification": "canonical",
      "canonical": "#97752",
      "candidate_fix": null,
      "title": null,
      "idempotency_key": "clownfish:live-pr-inventory-20260701T092542-001:#97753:merge_candidate:external_preflight:2db89e991ee14040f46dea3e1f46485097e96e5b",
      "source_status": "blocked",
      "source_reason": "external_merge_preflight_required",
      "reason": "action status is blocked",
      "merged_at": null,
      "merge_commit_sha": null,
      "expected_head_sha": null,
      "live_state": null,
      "live_updated_at": null,
      "apply_attempt": 1,
      "applied_at": "2026-07-01T09:34:56.856Z",
      "report_source": "apply"
    }
  ],
  "apply_audit_actions": [
    {
      "target": "#96122",
      "action": "merge_candidate",
      "status": "skipped",
      "classification": "canonical",
      "canonical": "#55888",
      "candidate_fix": null,
      "title": null,
      "idempotency_key": "clownfish:live-pr-inventory-20260701T092542-001:#96122:merge_candidate:external_preflight:a5b9f94eac35776b170a14daa7f0d4645698b8ac",
      "source_status": "blocked",
      "source_reason": "external_merge_preflight_required",
      "reason": "action status is blocked",
      "merged_at": null,
      "merge_commit_sha": null,
      "expected_head_sha": null,
      "live_state": null,
      "live_updated_at": null,
      "apply_attempt": 1,
      "applied_at": "2026-07-01T09:34:56.856Z",
      "report_source": "apply"
    },
    {
      "target": "#96275",
      "action": "merge_candidate",
      "status": "skipped",
      "classification": "canonical",
      "canonical": "#78495",
      "candidate_fix": null,
      "title": null,
      "idempotency_key": "clownfish:live-pr-inventory-20260701T092542-001:#96275:merge_candidate:external_preflight:720a6312fb0ece0da4418eb42b48d8e19c7b7d28",
      "source_status": "blocked",
      "source_reason": "external_merge_preflight_required",
      "reason": "action status is blocked",
      "merged_at": null,
      "merge_commit_sha": null,
      "expected_head_sha": null,
      "live_state": null,
      "live_updated_at": null,
      "apply_attempt": 1,
      "applied_at": "2026-07-01T09:34:56.856Z",
      "report_source": "apply"
    },
    {
      "target": "#96375",
      "action": "merge_candidate",
      "status": "skipped",
      "classification": "canonical",
      "canonical": null,
      "candidate_fix": null,
      "title": null,
      "idempotency_key": "clownfish:live-pr-inventory-20260701T092542-001:#96375:merge_candidate:external_preflight:d690d8967dc043b48a5359733ac1d1792110a42b",
      "source_status": "blocked",
      "source_reason": "external_merge_preflight_required",
      "reason": "action status is blocked",
      "merged_at": null,
      "merge_commit_sha": null,
      "expected_head_sha": null,
      "live_state": null,
      "live_updated_at": null,
      "apply_attempt": 1,
      "applied_at": "2026-07-01T09:34:56.856Z",
      "report_source": "apply"
    },
    {
      "target": "#97753",
      "action": "merge_candidate",
      "status": "skipped",
      "classification": "canonical",
      "canonical": "#97752",
      "candidate_fix": null,
      "title": null,
      "idempotency_key": "clownfish:live-pr-inventory-20260701T092542-001:#97753:merge_candidate:external_preflight:2db89e991ee14040f46dea3e1f46485097e96e5b",
      "source_status": "blocked",
      "source_reason": "external_merge_preflight_required",
      "reason": "action status is blocked",
      "merged_at": null,
      "merge_commit_sha": null,
      "expected_head_sha": null,
      "live_state": null,
      "live_updated_at": null,
      "apply_attempt": 1,
      "applied_at": "2026-07-01T09:34:56.856Z",
      "report_source": "apply"
    },
    {
      "target": "#96122",
      "action": "merge_candidate",
      "status": "skipped",
      "classification": "canonical",
      "canonical": "#55888",
      "candidate_fix": null,
      "title": null,
      "idempotency_key": "clownfish:live-pr-inventory-20260701T092542-001:#96122:merge_candidate:external_preflight:a5b9f94eac35776b170a14daa7f0d4645698b8ac",
      "source_status": "blocked",
      "source_reason": "external_merge_preflight_required",
      "reason": "action status is blocked",
      "merged_at": null,
      "merge_commit_sha": null,
      "expected_head_sha": null,
      "live_state": null,
      "live_updated_at": null,
      "apply_attempt": 2,
      "applied_at": "2026-07-01T09:34:57.013Z",
      "report_source": "apply"
    },
    {
      "target": "#96275",
      "action": "merge_candidate",
      "status": "skipped",
      "classification": "canonical",
      "canonical": "#78495",
      "candidate_fix": null,
      "title": null,
      "idempotency_key": "clownfish:live-pr-inventory-20260701T092542-001:#96275:merge_candidate:external_preflight:720a6312fb0ece0da4418eb42b48d8e19c7b7d28",
      "source_status": "blocked",
      "source_reason": "external_merge_preflight_required",
      "reason": "action status is blocked",
      "merged_at": null,
      "merge_commit_sha": null,
      "expected_head_sha": null,
      "live_state": null,
      "live_updated_at": null,
      "apply_attempt": 2,
      "applied_at": "2026-07-01T09:34:57.013Z",
      "report_source": "apply"
    },
    {
      "target": "#96375",
      "action": "merge_candidate",
      "status": "skipped",
      "classification": "canonical",
      "canonical": null,
      "candidate_fix": null,
      "title": null,
      "idempotency_key": "clownfish:live-pr-inventory-20260701T092542-001:#96375:merge_candidate:external_preflight:d690d8967dc043b48a5359733ac1d1792110a42b",
      "source_status": "blocked",
      "source_reason": "external_merge_preflight_required",
      "reason": "action status is blocked",
      "merged_at": null,
      "merge_commit_sha": null,
      "expected_head_sha": null,
      "live_state": null,
      "live_updated_at": null,
      "apply_attempt": 2,
      "applied_at": "2026-07-01T09:34:57.013Z",
      "report_source": "apply"
    },
    {
      "target": "#97753",
      "action": "merge_candidate",
      "status": "skipped",
      "classification": "canonical",
      "canonical": "#97752",
      "candidate_fix": null,
      "title": null,
      "idempotency_key": "clownfish:live-pr-inventory-20260701T092542-001:#97753:merge_candidate:external_preflight:2db89e991ee14040f46dea3e1f46485097e96e5b",
      "source_status": "blocked",
      "source_reason": "external_merge_preflight_required",
      "reason": "action status is blocked",
      "merged_at": null,
      "merge_commit_sha": null,
      "expected_head_sha": null,
      "live_state": null,
      "live_updated_at": null,
      "apply_attempt": 2,
      "applied_at": "2026-07-01T09:34:57.013Z",
      "report_source": "apply"
    }
  ]
}
