{
  "status": "dry_run",
  "generated_at": "2026-05-23T18:41:33.301Z",
  "repo": "openclaw/openclaw",
  "clownfish_repo": "openclaw/clownfish",
  "clawsweeper_repo": "openclaw/clawsweeper",
  "since": "2026-05-23T15:41:01.200Z",
  "execute": false,
  "max_comments": 100,
  "max_autoclose_targets": 8,
  "scanned_comments": 100,
  "commands_seen": 11,
  "actionable": 0,
  "trusted_bots": [
    "clawsweeper[bot]",
    "openclaw-clawsweeper[bot]"
  ],
  "allowed_repository_permissions": [
    "admin",
    "maintain",
    "write"
  ],
  "max_auto_repairs_per_head": 1,
  "max_auto_repairs_per_pr": 5,
  "commands": [
    {
      "idempotency_key": "clawsweeper-repair:openclaw/openclaw:85798:4526208445:2026-05-23T18:40:52Z:clawsweeper_auto_repair",
      "comment_id": "4526208445",
      "comment_node_id": "IC_kwDOQb6kR88AAAABDch1vQ",
      "comment_version_key": "4526208445:2026-05-23T18:40:52Z",
      "comment_url": "https://github.com/openclaw/openclaw/pull/85798#issuecomment-4526208445",
      "repo": "openclaw/openclaw",
      "issue_number": 85798,
      "author": "clawsweeper[bot]",
      "author_association": "CONTRIBUTOR",
      "comment_created_at": "2026-05-23T18:31:06Z",
      "comment_updated_at": "2026-05-23T18:40:52Z",
      "trigger": "trusted_bot",
      "command": "clawsweeper auto repair",
      "intent": "clawsweeper_auto_repair",
      "autoclose_message": null,
      "trusted_bot": true,
      "trusted_bot_author": "clawsweeper[bot]",
      "automation_source": "clawsweeper",
      "repair_reason": "structured ClawSweeper verdict: needs-human (sha=86c577bba4c6cd367bb0a586eb5288fef2f841f8)",
      "expected_head_sha": "86c577bba4c6cd367bb0a586eb5288fef2f841f8",
      "finding_id": null,
      "status": "skipped",
      "actions": [],
      "target": {
        "kind": "pull_request",
        "title": "fix(agents): actionable copy for exhausted auth-profile failover",
        "branch": "auth-profile-error-message",
        "head_sha": "86c577bba4c6cd367bb0a586eb5288fef2f841f8",
        "author": "romneyda",
        "labels": [
          "commands",
          "agents",
          "maintainer",
          "size: M",
          "P2",
          "rating: 🐚 platinum hermit",
          "status: 👀 ready for maintainer look"
        ],
        "is_clownfish_pr": false,
        "cluster_id": null,
        "job_path": null,
        "automerge_cluster_id": "automerge-openclaw-openclaw-85798",
        "automerge_job_path": "jobs/openclaw/inbox/automerge-openclaw-openclaw-85798.md",
        "mode": "autonomous",
        "merge_state_status": "UNSTABLE",
        "review_decision": "",
        "checks": {
          "total": 160,
          "counts": {
            "CANCELLED": 9,
            "IN_PROGRESS": 1,
            "SKIPPED": 71,
            "SUCCESS": 76,
            "FAILURE": 2,
            "NEUTRAL": 1
          },
          "blockers": [
            "auto-response:CANCELLED",
            "auto-response:CANCELLED",
            "auto-response:CANCELLED",
            "auto-response:CANCELLED",
            "auto-response:CANCELLED",
            "Real behavior proof:CANCELLED",
            "Real behavior proof:CANCELLED",
            "Real behavior proof:CANCELLED",
            "Real behavior proof:CANCELLED",
            "Real behavior proof:IN_PROGRESS",
            "checks-node-core-fast:FAILURE",
            "checks-node-agentic-control-plane-runtime:FAILURE"
          ]
        }
      },
      "reason": "repair commands require a Clownfish PR or a PR opted into Clownfish automerge"
    },
    {
      "idempotency_key": "clawsweeper-repair:openclaw/openclaw:85796:4526174606:2026-05-23T18:25:17Z:clawsweeper_auto_repair",
      "comment_id": "4526174606",
      "comment_node_id": "IC_kwDOQb6kR88AAAABDcfxjg",
      "comment_version_key": "4526174606:2026-05-23T18:25:17Z",
      "comment_url": "https://github.com/openclaw/openclaw/pull/85796#issuecomment-4526174606",
      "repo": "openclaw/openclaw",
      "issue_number": 85796,
      "author": "clawsweeper[bot]",
      "author_association": "CONTRIBUTOR",
      "comment_created_at": "2026-05-23T18:15:32Z",
      "comment_updated_at": "2026-05-23T18:25:17Z",
      "trigger": "trusted_bot",
      "command": "clawsweeper auto repair",
      "intent": "clawsweeper_auto_repair",
      "autoclose_message": null,
      "trusted_bot": true,
      "trusted_bot_author": "clawsweeper[bot]",
      "automation_source": "clawsweeper",
      "repair_reason": "structured ClawSweeper verdict: needs-human (sha=65534e80cbf3474c4efcf511400105d70be53d17)",
      "expected_head_sha": "65534e80cbf3474c4efcf511400105d70be53d17",
      "finding_id": null,
      "status": "skipped",
      "actions": [],
      "target": {
        "kind": "pull_request",
        "title": "fix(twitch): evict client manager on disconnect failure",
        "branch": "fix/issue-83886-twitch-registry-cleanup",
        "head_sha": "65534e80cbf3474c4efcf511400105d70be53d17",
        "author": "brokemac79",
        "labels": [
          "channel: twitch",
          "size: XS",
          "proof: supplied",
          "proof: sufficient",
          "P2",
          "rating: 🦞 diamond lobster",
          "status: 👀 ready for maintainer look"
        ],
        "is_clownfish_pr": false,
        "cluster_id": null,
        "job_path": null,
        "automerge_cluster_id": "automerge-openclaw-openclaw-85796",
        "automerge_job_path": "jobs/openclaw/inbox/automerge-openclaw-openclaw-85796.md",
        "mode": "autonomous",
        "merge_state_status": "UNKNOWN",
        "review_decision": "",
        "checks": {
          "total": 171,
          "counts": {
            "FAILURE": 3,
            "CANCELLED": 11,
            "SKIPPED": 82,
            "SUCCESS": 74,
            "NEUTRAL": 1
          },
          "blockers": [
            "Real behavior proof:FAILURE",
            "auto-response:CANCELLED",
            "auto-response:CANCELLED",
            "auto-response:CANCELLED",
            "auto-response:CANCELLED",
            "auto-response:CANCELLED",
            "Real behavior proof:CANCELLED",
            "Real behavior proof:CANCELLED",
            "Real behavior proof:CANCELLED",
            "Real behavior proof:CANCELLED",
            "Real behavior proof:CANCELLED",
            "Real behavior proof:CANCELLED",
            "checks-node-core-fast:FAILURE",
            "checks-node-agentic-control-plane-runtime:FAILURE"
          ]
        }
      },
      "reason": "repair commands require a Clownfish PR or a PR opted into Clownfish automerge"
    },
    {
      "idempotency_key": "clawsweeper-repair:openclaw/openclaw:85795:4526162534:2026-05-23T18:27:31Z:clawsweeper_auto_repair",
      "comment_id": "4526162534",
      "comment_node_id": "IC_kwDOQb6kR88AAAABDcfCZg",
      "comment_version_key": "4526162534:2026-05-23T18:27:31Z",
      "comment_url": "https://github.com/openclaw/openclaw/pull/85795#issuecomment-4526162534",
      "repo": "openclaw/openclaw",
      "issue_number": 85795,
      "author": "clawsweeper[bot]",
      "author_association": "CONTRIBUTOR",
      "comment_created_at": "2026-05-23T18:09:49Z",
      "comment_updated_at": "2026-05-23T18:27:31Z",
      "trigger": "trusted_bot",
      "command": "clawsweeper auto repair",
      "intent": "clawsweeper_auto_repair",
      "autoclose_message": null,
      "trusted_bot": true,
      "trusted_bot_author": "clawsweeper[bot]",
      "automation_source": "clawsweeper",
      "repair_reason": "structured ClawSweeper verdict: needs-human (sha=042bd01c14cee97afeb75f2f99a39ced0a768b26)",
      "expected_head_sha": "042bd01c14cee97afeb75f2f99a39ced0a768b26",
      "finding_id": null,
      "status": "skipped",
      "actions": [],
      "target": {
        "kind": "pull_request",
        "title": "Docs: add policy rule reference tables",
        "branch": "policy-doc-reference-tables",
        "head_sha": "042bd01c14cee97afeb75f2f99a39ced0a768b26",
        "author": "giodl73-repo",
        "labels": [
          "docs",
          "maintainer",
          "size: XL",
          "proof: sufficient",
          "P2",
          "rating: 🐚 platinum hermit",
          "merge-risk: 🚨 compatibility",
          "merge-risk: 🚨 security-boundary",
          "status: 👀 ready for maintainer look",
          "extensions: policy"
        ],
        "is_clownfish_pr": false,
        "cluster_id": null,
        "job_path": null,
        "automerge_cluster_id": "automerge-openclaw-openclaw-85795",
        "automerge_job_path": "jobs/openclaw/inbox/automerge-openclaw-openclaw-85795.md",
        "mode": "autonomous",
        "merge_state_status": "UNSTABLE",
        "review_decision": "",
        "checks": {
          "total": 216,
          "counts": {
            "CANCELLED": 9,
            "SKIPPED": 127,
            "SUCCESS": 70,
            "IN_PROGRESS": 6,
            "FAILURE": 3,
            "NEUTRAL": 1
          },
          "blockers": [
            "auto-response:CANCELLED",
            "auto-response:CANCELLED",
            "auto-response:CANCELLED",
            "auto-response:CANCELLED",
            "auto-response:CANCELLED",
            "Real behavior proof:CANCELLED",
            "Real behavior proof:CANCELLED",
            "Real behavior proof:CANCELLED",
            "Real behavior proof:CANCELLED",
            "Security High (channel-runtime-boundary):IN_PROGRESS",
            "build-artifacts:IN_PROGRESS",
            "checks-fast-bundled-protocol:FAILURE",
            "checks-node-core-fast:FAILURE",
            "Critical Quality (network-runtime-boundary):IN_PROGRESS",
            "checks-node-core-runtime-cron-isolated-agent:IN_PROGRESS",
            "checks-node-agentic-control-plane-runtime:IN_PROGRESS",
            "checks-node-agentic-commands-models:FAILURE",
            "check-additional-boundaries-a:IN_PROGRESS"
          ]
        }
      },
      "reason": "repair commands require a Clownfish PR or a PR opted into Clownfish automerge"
    },
    {
      "idempotency_key": "clawsweeper-repair:openclaw/openclaw:85794:4526162110:2026-05-23T18:17:07Z:clawsweeper_auto_repair",
      "comment_id": "4526162110",
      "comment_node_id": "IC_kwDOQb6kR88AAAABDcfAvg",
      "comment_version_key": "4526162110:2026-05-23T18:17:07Z",
      "comment_url": "https://github.com/openclaw/openclaw/pull/85794#issuecomment-4526162110",
      "repo": "openclaw/openclaw",
      "issue_number": 85794,
      "author": "clawsweeper[bot]",
      "author_association": "CONTRIBUTOR",
      "comment_created_at": "2026-05-23T18:09:37Z",
      "comment_updated_at": "2026-05-23T18:17:07Z",
      "trigger": "trusted_bot",
      "command": "clawsweeper auto repair",
      "intent": "clawsweeper_auto_repair",
      "autoclose_message": null,
      "trusted_bot": true,
      "trusted_bot_author": "clawsweeper[bot]",
      "automation_source": "clawsweeper",
      "repair_reason": "structured ClawSweeper verdict: needs-human (sha=c3fa89a74dcdbf0471723869372eede3e04d112f)",
      "expected_head_sha": "c3fa89a74dcdbf0471723869372eede3e04d112f",
      "finding_id": null,
      "status": "skipped",
      "actions": [],
      "target": {
        "kind": "pull_request",
        "title": "fix(twitch): fail fast when auth provider cannot bind user",
        "branch": "fix-83853-twitch-auth-bind-failure",
        "head_sha": "c3fa89a74dcdbf0471723869372eede3e04d112f",
        "author": "alkor2000",
        "labels": [
          "channel: twitch",
          "size: XS",
          "proof: supplied",
          "P1",
          "rating: 🦐 gold shrimp",
          "merge-risk: 🚨 auth-provider",
          "status: 📣 needs proof"
        ],
        "is_clownfish_pr": false,
        "cluster_id": null,
        "job_path": null,
        "automerge_cluster_id": "automerge-openclaw-openclaw-85794",
        "automerge_job_path": "jobs/openclaw/inbox/automerge-openclaw-openclaw-85794.md",
        "mode": "autonomous",
        "merge_state_status": "UNKNOWN",
        "review_decision": "",
        "checks": {
          "total": 152,
          "counts": {
            "CANCELLED": 7,
            "SKIPPED": 72,
            "SUCCESS": 68,
            "FAILURE": 4,
            "NEUTRAL": 1
          },
          "blockers": [
            "auto-response:CANCELLED",
            "auto-response:CANCELLED",
            "auto-response:CANCELLED",
            "Real behavior proof:CANCELLED",
            "Real behavior proof:CANCELLED",
            "Real behavior proof:CANCELLED",
            "Real behavior proof:CANCELLED",
            "checks-node-core-fast:FAILURE",
            "checks-node-core-runtime-cron-isolated-agent:FAILURE",
            "checks-node-agentic-control-plane-runtime:FAILURE",
            "check-additional-boundaries-a:FAILURE"
          ]
        }
      },
      "reason": "repair commands require a Clownfish PR or a PR opted into Clownfish automerge"
    },
    {
      "idempotency_key": "clawsweeper-repair:openclaw/openclaw:85793:4526119844:2026-05-23T18:15:12Z:clawsweeper_auto_repair",
      "comment_id": "4526119844",
      "comment_node_id": "IC_kwDOQb6kR88AAAABDccbpA",
      "comment_version_key": "4526119844:2026-05-23T18:15:12Z",
      "comment_url": "https://github.com/openclaw/openclaw/pull/85793#issuecomment-4526119844",
      "repo": "openclaw/openclaw",
      "issue_number": 85793,
      "author": "clawsweeper[bot]",
      "author_association": "CONTRIBUTOR",
      "comment_created_at": "2026-05-23T17:49:39Z",
      "comment_updated_at": "2026-05-23T18:15:12Z",
      "trigger": "trusted_bot",
      "command": "clawsweeper auto repair",
      "intent": "clawsweeper_auto_repair",
      "autoclose_message": null,
      "trusted_bot": true,
      "trusted_bot_author": "clawsweeper[bot]",
      "automation_source": "clawsweeper",
      "repair_reason": "structured ClawSweeper verdict: needs-human (sha=3b562a08d7f0f20d03f6be0b38257fe9bff3eaa6)",
      "expected_head_sha": "3b562a08d7f0f20d03f6be0b38257fe9bff3eaa6",
      "finding_id": null,
      "status": "skipped",
      "actions": [],
      "target": {
        "kind": "pull_request",
        "title": "docs(github): make post-install restart explicit",
        "branch": "docs/github-skill-restart-guidance",
        "head_sha": "3b562a08d7f0f20d03f6be0b38257fe9bff3eaa6",
        "author": "nielskaspers",
        "labels": [
          "size: XS",
          "triage: needs-real-behavior-proof",
          "P3",
          "rating: 🦪 silver shellfish",
          "status: 📣 needs proof"
        ],
        "is_clownfish_pr": false,
        "cluster_id": null,
        "job_path": null,
        "automerge_cluster_id": "automerge-openclaw-openclaw-85793",
        "automerge_job_path": "jobs/openclaw/inbox/automerge-openclaw-openclaw-85793.md",
        "mode": "autonomous",
        "merge_state_status": "UNKNOWN",
        "review_decision": "",
        "checks": {
          "total": 73,
          "counts": {
            "FAILURE": 3,
            "CANCELLED": 6,
            "SKIPPED": 51,
            "SUCCESS": 13
          },
          "blockers": [
            "Real behavior proof:FAILURE",
            "Real behavior proof:FAILURE",
            "Real behavior proof:FAILURE",
            "auto-response:CANCELLED",
            "auto-response:CANCELLED",
            "auto-response:CANCELLED",
            "Real behavior proof:CANCELLED",
            "Real behavior proof:CANCELLED",
            "Real behavior proof:CANCELLED"
          ]
        }
      },
      "reason": "repair commands require a Clownfish PR or a PR opted into Clownfish automerge"
    },
    {
      "idempotency_key": "clawsweeper-repair:openclaw/openclaw:85784:4526100600:2026-05-23T17:48:40Z:clawsweeper_auto_repair",
      "comment_id": "4526100600",
      "comment_node_id": "IC_kwDOQb6kR88AAAABDcbQeA",
      "comment_version_key": "4526100600:2026-05-23T17:48:40Z",
      "comment_url": "https://github.com/openclaw/openclaw/pull/85784#issuecomment-4526100600",
      "repo": "openclaw/openclaw",
      "issue_number": 85784,
      "author": "clawsweeper[bot]",
      "author_association": "CONTRIBUTOR",
      "comment_created_at": "2026-05-23T17:40:23Z",
      "comment_updated_at": "2026-05-23T17:48:40Z",
      "trigger": "trusted_bot",
      "command": "clawsweeper auto repair",
      "intent": "clawsweeper_auto_repair",
      "autoclose_message": null,
      "trusted_bot": true,
      "trusted_bot_author": "clawsweeper[bot]",
      "automation_source": "clawsweeper",
      "repair_reason": "structured ClawSweeper verdict: needs-human (sha=6abde6433d665f15dc9d2a75420513bfb1fd50b4)",
      "expected_head_sha": "6abde6433d665f15dc9d2a75420513bfb1fd50b4",
      "finding_id": null,
      "status": "skipped",
      "actions": [],
      "target": {
        "kind": "pull_request",
        "title": "fix(telegram): debounce media messages to coalesce rapid sends into one agent turn",
        "branch": "fix/media-debounce-coalesce",
        "head_sha": "6abde6433d665f15dc9d2a75420513bfb1fd50b4",
        "author": "moeedahmed",
        "labels": [
          "size: XS",
          "triage: needs-real-behavior-proof",
          "mantis: telegram-visible-proof",
          "P2",
          "rating: 🧂 unranked krab",
          "merge-risk: 🚨 message-delivery",
          "status: 📣 needs proof"
        ],
        "is_clownfish_pr": false,
        "cluster_id": null,
        "job_path": null,
        "automerge_cluster_id": "automerge-openclaw-openclaw-85784",
        "automerge_job_path": "jobs/openclaw/inbox/automerge-openclaw-openclaw-85784.md",
        "mode": "autonomous",
        "merge_state_status": "UNKNOWN",
        "review_decision": "",
        "checks": {
          "total": 70,
          "counts": {
            "FAILURE": 5,
            "CANCELLED": 6,
            "SKIPPED": 47,
            "SUCCESS": 10,
            "NEUTRAL": 2
          },
          "blockers": [
            "Real behavior proof:FAILURE",
            "Real behavior proof:FAILURE",
            "Real behavior proof:FAILURE",
            "Real behavior proof:FAILURE",
            "auto-response:CANCELLED",
            "auto-response:CANCELLED",
            "auto-response:CANCELLED",
            "Real behavior proof:CANCELLED",
            "Real behavior proof:CANCELLED",
            "Real behavior proof:CANCELLED",
            "Run agentic native Telegram proof:FAILURE"
          ]
        }
      },
      "reason": "repair commands require a Clownfish PR or a PR opted into Clownfish automerge"
    },
    {
      "idempotency_key": "clawsweeper-repair:openclaw/openclaw:85791:4526096763:2026-05-23T17:55:13Z:clawsweeper_auto_repair",
      "comment_id": "4526096763",
      "comment_node_id": "IC_kwDOQb6kR88AAAABDcbBew",
      "comment_version_key": "4526096763:2026-05-23T17:55:13Z",
      "comment_url": "https://github.com/openclaw/openclaw/pull/85791#issuecomment-4526096763",
      "repo": "openclaw/openclaw",
      "issue_number": 85791,
      "author": "clawsweeper[bot]",
      "author_association": "CONTRIBUTOR",
      "comment_created_at": "2026-05-23T17:38:39Z",
      "comment_updated_at": "2026-05-23T17:55:13Z",
      "trigger": "trusted_bot",
      "command": "clawsweeper auto repair",
      "intent": "clawsweeper_auto_repair",
      "autoclose_message": null,
      "trusted_bot": true,
      "trusted_bot_author": "clawsweeper[bot]",
      "automation_source": "clawsweeper",
      "repair_reason": "structured ClawSweeper verdict: needs-human (sha=25bc9741c22ace0edd7314fc47889e8282004013)",
      "expected_head_sha": "25bc9741c22ace0edd7314fc47889e8282004013",
      "finding_id": null,
      "status": "skipped",
      "actions": [],
      "target": {
        "kind": "pull_request",
        "title": "fix(gateway): dedupe probe warnings by gateway identity",
        "branch": "fix-69135-gateway-probe-identity",
        "head_sha": "25bc9741c22ace0edd7314fc47889e8282004013",
        "author": "giodl73-repo",
        "labels": [
          "commands",
          "maintainer",
          "size: M",
          "P2",
          "rating: 🦪 silver shellfish",
          "status: 📣 needs proof"
        ],
        "is_clownfish_pr": false,
        "cluster_id": null,
        "job_path": null,
        "automerge_cluster_id": "automerge-openclaw-openclaw-85791",
        "automerge_job_path": "jobs/openclaw/inbox/automerge-openclaw-openclaw-85791.md",
        "mode": "autonomous",
        "merge_state_status": "UNSTABLE",
        "review_decision": "",
        "checks": {
          "total": 151,
          "counts": {
            "FAILURE": 3,
            "CANCELLED": 9,
            "SKIPPED": 65,
            "SUCCESS": 73,
            "NEUTRAL": 1
          },
          "blockers": [
            "Scan changed paths (precise):FAILURE",
            "auto-response:CANCELLED",
            "auto-response:CANCELLED",
            "auto-response:CANCELLED",
            "auto-response:CANCELLED",
            "Real behavior proof:CANCELLED",
            "Real behavior proof:CANCELLED",
            "Real behavior proof:CANCELLED",
            "Real behavior proof:CANCELLED",
            "Real behavior proof:CANCELLED",
            "checks-node-core-fast:FAILURE",
            "checks-node-agentic-control-plane-runtime:FAILURE"
          ]
        }
      },
      "reason": "repair commands require a Clownfish PR or a PR opted into Clownfish automerge"
    },
    {
      "idempotency_key": "clawsweeper-repair:openclaw/openclaw:85788:4526044948:2026-05-23T18:21:45Z:clawsweeper_auto_repair",
      "comment_id": "4526044948",
      "comment_node_id": "IC_kwDOQb6kR88AAAABDcX3FA",
      "comment_version_key": "4526044948:2026-05-23T18:21:45Z",
      "comment_url": "https://github.com/openclaw/openclaw/pull/85788#issuecomment-4526044948",
      "repo": "openclaw/openclaw",
      "issue_number": 85788,
      "author": "clawsweeper[bot]",
      "author_association": "CONTRIBUTOR",
      "comment_created_at": "2026-05-23T17:15:22Z",
      "comment_updated_at": "2026-05-23T18:21:45Z",
      "trigger": "trusted_bot",
      "command": "clawsweeper auto repair",
      "intent": "clawsweeper_auto_repair",
      "autoclose_message": null,
      "trusted_bot": true,
      "trusted_bot_author": "clawsweeper[bot]",
      "automation_source": "clawsweeper",
      "repair_reason": "structured ClawSweeper verdict: needs-human (sha=02be8d8bbbf5a2bed842387ea023d046ab761d86)",
      "expected_head_sha": "02be8d8bbbf5a2bed842387ea023d046ab761d86",
      "finding_id": null,
      "status": "skipped",
      "actions": [],
      "target": {
        "kind": "pull_request",
        "title": "Fix/spawned by cache leak",
        "branch": "fix/spawned-by-cache-leak",
        "head_sha": "02be8d8bbbf5a2bed842387ea023d046ab761d86",
        "author": "georgeboiko",
        "labels": [
          "gateway",
          "size: S",
          "proof: supplied",
          "P1",
          "rating: 🦪 silver shellfish",
          "status: 📣 needs proof"
        ],
        "is_clownfish_pr": false,
        "cluster_id": null,
        "job_path": null,
        "automerge_cluster_id": "automerge-openclaw-openclaw-85788",
        "automerge_job_path": "jobs/openclaw/inbox/automerge-openclaw-openclaw-85788.md",
        "mode": "autonomous",
        "merge_state_status": "UNKNOWN",
        "review_decision": "",
        "checks": {
          "total": 128,
          "counts": {
            "FAILURE": 6,
            "CANCELLED": 2,
            "SKIPPED": 37,
            "SUCCESS": 82,
            "NEUTRAL": 1
          },
          "blockers": [
            "Real behavior proof:FAILURE",
            "Real behavior proof:FAILURE",
            "Real behavior proof:FAILURE",
            "auto-response:CANCELLED",
            "Real behavior proof:CANCELLED",
            "checks-node-core-fast:FAILURE",
            "checks-node-agentic-control-plane-runtime:FAILURE",
            "checks-node-agentic-command-support:FAILURE"
          ]
        }
      },
      "reason": "repair commands require a Clownfish PR or a PR opted into Clownfish automerge"
    },
    {
      "idempotency_key": "clawsweeper-repair:openclaw/openclaw:85787:4526042641:2026-05-23T17:46:22Z:clawsweeper_auto_repair",
      "comment_id": "4526042641",
      "comment_node_id": "IC_kwDOQb6kR88AAAABDcXuEQ",
      "comment_version_key": "4526042641:2026-05-23T17:46:22Z",
      "comment_url": "https://github.com/openclaw/openclaw/pull/85787#issuecomment-4526042641",
      "repo": "openclaw/openclaw",
      "issue_number": 85787,
      "author": "clawsweeper[bot]",
      "author_association": "CONTRIBUTOR",
      "comment_created_at": "2026-05-23T17:14:17Z",
      "comment_updated_at": "2026-05-23T17:46:22Z",
      "trigger": "trusted_bot",
      "command": "clawsweeper auto repair",
      "intent": "clawsweeper_auto_repair",
      "autoclose_message": null,
      "trusted_bot": true,
      "trusted_bot_author": "clawsweeper[bot]",
      "automation_source": "clawsweeper",
      "repair_reason": "structured ClawSweeper verdict: needs-human (sha=ce15b405545e19431b74a7bca8a6d6da6f3c5685)",
      "expected_head_sha": "ce15b405545e19431b74a7bca8a6d6da6f3c5685",
      "finding_id": null,
      "status": "skipped",
      "actions": [],
      "target": {
        "kind": "pull_request",
        "title": "fix(config): do not suppress recovery retry after failed backup restore",
        "branch": "fix/config-recovery-retry-suppression",
        "head_sha": "ce15b405545e19431b74a7bca8a6d6da6f3c5685",
        "author": "sebtardif",
        "labels": [
          "size: S",
          "proof: supplied",
          "proof: sufficient",
          "P2",
          "rating: 🐚 platinum hermit",
          "status: 👀 ready for maintainer look"
        ],
        "is_clownfish_pr": false,
        "cluster_id": null,
        "job_path": null,
        "automerge_cluster_id": "automerge-openclaw-openclaw-85787",
        "automerge_job_path": "jobs/openclaw/inbox/automerge-openclaw-openclaw-85787.md",
        "mode": "autonomous",
        "merge_state_status": "UNKNOWN",
        "review_decision": "",
        "checks": {
          "total": 152,
          "counts": {
            "FAILURE": 2,
            "CANCELLED": 8,
            "SKIPPED": 65,
            "SUCCESS": 76,
            "NEUTRAL": 1
          },
          "blockers": [
            "dependency-change-awareness:FAILURE",
            "auto-response:CANCELLED",
            "auto-response:CANCELLED",
            "auto-response:CANCELLED",
            "auto-response:CANCELLED",
            "Real behavior proof:CANCELLED",
            "Real behavior proof:CANCELLED",
            "Real behavior proof:CANCELLED",
            "Real behavior proof:CANCELLED",
            "checks-node-core-fast:FAILURE"
          ]
        }
      },
      "reason": "repair commands require a Clownfish PR or a PR opted into Clownfish automerge"
    },
    {
      "idempotency_key": "clawsweeper-repair:openclaw/openclaw:85786:4526013042:2026-05-23T17:46:15Z:clawsweeper_auto_repair",
      "comment_id": "4526013042",
      "comment_node_id": "IC_kwDOQb6kR88AAAABDcV6cg",
      "comment_version_key": "4526013042:2026-05-23T17:46:15Z",
      "comment_url": "https://github.com/openclaw/openclaw/pull/85786#issuecomment-4526013042",
      "repo": "openclaw/openclaw",
      "issue_number": 85786,
      "author": "clawsweeper[bot]",
      "author_association": "CONTRIBUTOR",
      "comment_created_at": "2026-05-23T17:01:22Z",
      "comment_updated_at": "2026-05-23T17:46:15Z",
      "trigger": "trusted_bot",
      "command": "clawsweeper auto repair",
      "intent": "clawsweeper_auto_repair",
      "autoclose_message": null,
      "trusted_bot": true,
      "trusted_bot_author": "clawsweeper[bot]",
      "automation_source": "clawsweeper",
      "repair_reason": "structured ClawSweeper verdict: needs-human (sha=69916a729397b32065d108bdc11138b0119b2117)",
      "expected_head_sha": "69916a729397b32065d108bdc11138b0119b2117",
      "finding_id": null,
      "status": "skipped",
      "actions": [],
      "target": {
        "kind": "pull_request",
        "title": "fix(ui): show failed tool results as errors",
        "branch": "fix/nemoclaw-2621-tool-error-status",
        "head_sha": "69916a729397b32065d108bdc11138b0119b2117",
        "author": "chengjiew",
        "labels": [
          "app: web-ui",
          "size: L",
          "proof: sufficient",
          "P2",
          "rating: 🐚 platinum hermit",
          "merge-risk: 🚨 compatibility",
          "status: 👀 ready for maintainer look"
        ],
        "is_clownfish_pr": false,
        "cluster_id": null,
        "job_path": null,
        "automerge_cluster_id": "automerge-openclaw-openclaw-85786",
        "automerge_job_path": "jobs/openclaw/inbox/automerge-openclaw-openclaw-85786.md",
        "mode": "autonomous",
        "merge_state_status": "UNKNOWN",
        "review_decision": "",
        "checks": {
          "total": 146,
          "counts": {
            "FAILURE": 7,
            "CANCELLED": 10,
            "SKIPPED": 67,
            "SUCCESS": 62
          },
          "blockers": [
            "Real behavior proof:FAILURE",
            "Real behavior proof:FAILURE",
            "Real behavior proof:FAILURE",
            "Real behavior proof:FAILURE",
            "auto-response:CANCELLED",
            "auto-response:CANCELLED",
            "auto-response:CANCELLED",
            "auto-response:CANCELLED",
            "auto-response:CANCELLED",
            "Real behavior proof:CANCELLED",
            "Real behavior proof:CANCELLED",
            "Real behavior proof:CANCELLED",
            "Real behavior proof:CANCELLED",
            "Real behavior proof:CANCELLED",
            "checks-node-core-fast:FAILURE",
            "checks-node-core-runtime-media-ui:FAILURE",
            "check-test-types:FAILURE"
          ]
        }
      },
      "reason": "repair commands require a Clownfish PR or a PR opted into Clownfish automerge"
    },
    {
      "idempotency_key": "clawsweeper-repair:openclaw/openclaw:85785:4526002864:2026-05-23T17:18:26Z:clawsweeper_auto_repair",
      "comment_id": "4526002864",
      "comment_node_id": "IC_kwDOQb6kR88AAAABDcVSsA",
      "comment_version_key": "4526002864:2026-05-23T17:18:26Z",
      "comment_url": "https://github.com/openclaw/openclaw/pull/85785#issuecomment-4526002864",
      "repo": "openclaw/openclaw",
      "issue_number": 85785,
      "author": "clawsweeper[bot]",
      "author_association": "CONTRIBUTOR",
      "comment_created_at": "2026-05-23T16:56:19Z",
      "comment_updated_at": "2026-05-23T17:18:26Z",
      "trigger": "trusted_bot",
      "command": "clawsweeper auto repair",
      "intent": "clawsweeper_auto_repair",
      "autoclose_message": null,
      "trusted_bot": true,
      "trusted_bot_author": "clawsweeper[bot]",
      "automation_source": "clawsweeper",
      "repair_reason": "structured ClawSweeper verdict: needs-human (sha=cc001344a4def746e1aa0a4f4daa45882613ad5d)",
      "expected_head_sha": "cc001344a4def746e1aa0a4f4daa45882613ad5d",
      "finding_id": null,
      "status": "skipped",
      "actions": [],
      "target": {
        "kind": "pull_request",
        "title": "fix(plugins): return plugin gateway method results",
        "branch": "fix-59470-plugin-gateway-call-return",
        "head_sha": "cc001344a4def746e1aa0a4f4daa45882613ad5d",
        "author": "giodl73-repo",
        "labels": [
          "maintainer",
          "size: S",
          "P2",
          "rating: 🦪 silver shellfish",
          "merge-risk: 🚨 compatibility",
          "status: 📣 needs proof"
        ],
        "is_clownfish_pr": false,
        "cluster_id": null,
        "job_path": null,
        "automerge_cluster_id": "automerge-openclaw-openclaw-85785",
        "automerge_job_path": "jobs/openclaw/inbox/automerge-openclaw-openclaw-85785.md",
        "mode": "autonomous",
        "merge_state_status": "UNSTABLE",
        "review_decision": "",
        "checks": {
          "total": 149,
          "counts": {
            "CANCELLED": 5,
            "SKIPPED": 64,
            "SUCCESS": 76,
            "FAILURE": 3,
            "NEUTRAL": 1
          },
          "blockers": [
            "auto-response:CANCELLED",
            "Real behavior proof:CANCELLED",
            "Real behavior proof:CANCELLED",
            "Real behavior proof:CANCELLED",
            "Real behavior proof:CANCELLED",
            "checks-node-core-fast:FAILURE",
            "check-lint:FAILURE",
            "check-test-types:FAILURE"
          ]
        }
      },
      "reason": "repair commands require a Clownfish PR or a PR opted into Clownfish automerge"
    }
  ]
}
